zimran/events/__init__.py
zimran/events/connection.py
zimran/events/constants.py
zimran/events/consumer.py
zimran/events/dto.py
zimran/events/exceptions.py
zimran/events/patterns.py
zimran/events/producer.py
zimran/events/router.py
zimran/events/schemas.py
zimran/events/utils.py
zimran_events-0.6.0.dist-info/LICENSE
zimran_events-0.6.0.dist-info/METADATA
zimran_events-0.6.0.dist-info/WHEEL
zimran_events-0.6.0.dist-info/top_level.txt
zimran_events-0.6.0.dist-info/RECORD
