Metadata-Version: 2.1
Name: zimran-events
Version: 0.6.0
Summary: The zimran-events provides amqp interface
Author-email: Talgat Abdraimov <abdraimov.talga@gmail.com>
License: MIT License
Project-URL: homepage, https://github.com/zimran-tech/zimran-py-events
Project-URL: repository, https://github.com/zimran-tech/zimran-py-events.git
Project-URL: bugtracker, https://github.com/zimran-tech/zimran-py-events/issues
Project-URL: changelog, https://github.com/zimran-tech/zimran-py-events/releases
Classifier: Development Status :: 3 - Alpha
Classifier: Environment :: Web Environment
Classifier: Intended Audience :: Developers
Classifier: License :: OSI Approved :: MIT License
Classifier: Operating System :: OS Independent
Classifier: Programming Language :: Python
Requires-Python: >=3.10
License-File: LICENSE
Requires-Dist: pika ==1.3.2
Requires-Dist: aio-pika ==9.4.3
Requires-Dist: aioretry ==5.0.6
Provides-Extra: dev
Requires-Dist: black ; extra == 'dev'
Requires-Dist: pytest ; extra == 'dev'
Requires-Dist: pytest-cov ; extra == 'dev'
Requires-Dist: flake8 ; extra == 'dev'
Requires-Dist: flake8-print ; extra == 'dev'
Requires-Dist: flake8-multiline-containers ; extra == 'dev'
Requires-Dist: flake8-builtins ; extra == 'dev'
Requires-Dist: flake8-import-order ; extra == 'dev'
Requires-Dist: flake8-commas ; extra == 'dev'
Requires-Dist: flake8-quotes ; extra == 'dev'
